fmricat/RC.py
fmricat/__init__.py
fmricat/denoiser.py
fmricat-0.0.1.dist-info/entry_points.txt
fmricat-0.0.1.dist-info/WHEEL
fmricat-0.0.1.dist-info/METADATA
fmricat-0.0.1.dist-info/RECORD
